{
   "tools": "ati18n",
   "version": "0.1.0",
   "app_path": "/workspaces/ati18n",
   "app_type": "java",
   "datetime": "2022-04-26 12:31:09",
   "result": [
      {
         "No": "1001",
         "Level": "错误",
         "Scope": "整体翻译",
         "Name": "翻译条目数不匹配",
         "Data": {
            "type": "flie",
            "file_path": "messages_en.properties"
         },
         "Comment": ""
      },
      {
         "No": "1001",
         "Level": "错误",
         "Scope": "整体翻译",
         "Name": "翻译条目数不匹配",
         "Data": {
            "type": "flie",
            "file_path": "messages_zh_CN.properties"
         },
         "Comment": ""
      }
   ]
}